dataengineeringutils3/__init__.py
dataengineeringutils3/db.py
dataengineeringutils3/json.py
dataengineeringutils3/logging.py
dataengineeringutils3/pulumi.py
dataengineeringutils3/s3.py
dataengineeringutils3/writer.py
dataengineeringutils3-1.4.3.dist-info/LICENSE
dataengineeringutils3-1.4.3.dist-info/METADATA
dataengineeringutils3-1.4.3.dist-info/WHEEL
dataengineeringutils3-1.4.3.dist-info/RECORD
